rtd_poetry.py
rtd_poetry-0.1.0.dist-info/WHEEL
rtd_poetry-0.1.0.dist-info/METADATA
rtd_poetry-0.1.0.dist-info/RECORD
