Metadata-Version: 2.1
Name: rtd-poetry
Version: 0.1.0
Summary: Execute poetry install with dev dependencies on RTD
Author: Chris Hunt
Author-email: chrahunt@gmail.com
Requires-Python: >=3.6,<4.0
Classifier: Programming Language :: Python :: 3
Classifier: Programming Language :: Python :: 3.6
Classifier: Programming Language :: Python :: 3.7
